pytelematics_oasa/__init__.py
pytelematics_oasa/api.py
pytelematics_oasa/exception.py
pytelematics_oasa-1.0.0.dist-info/LICENSE
pytelematics_oasa-1.0.0.dist-info/METADATA
pytelematics_oasa-1.0.0.dist-info/WHEEL
pytelematics_oasa-1.0.0.dist-info/top_level.txt
pytelematics_oasa-1.0.0.dist-info/RECORD
