Metadata-Version: 2.1
Name: pytelematics-oasa
Version: 1.0.0
Summary: OASA Telematics API wrapper for python.
Home-page: https://github.com/blackrose514/pytelematics-oasa
Author: blackrose514
Author-email: dmtri3sukuna@gmail.com
License: MIT
Download-URL: https://github.com/blackrose514/pytelematics-oasa/releases
Keywords: oasa,telematics,api,pytelematics-oasa
Platform: UNKNOWN
Classifier: Programming Language :: Python :: 3
Classifier: Programming Language :: Python :: 3.6
Classifier: Programming Language :: Python :: 3.7
Classifier: License :: OSI Approved :: MIT License
Classifier: Operating System :: OS Independent
Requires-Dist: requests
